{"Blocks":{"240v-duplex":{"Att":{"Annotative":true,"Dynamic":false,"Explode":true,"InsUnit":1,"ScaleUniformly":true},"Previews":{"72_64_64_0":{"Checksum":"be7b7292f82d3e3cd3b286de4bdcd1504a0fd4ac","URL":"one-240v-duplex-y-orientation.dwg.240v-duplex.72_64_64_0.png"}}}},"Header":{"Att":{"Annotative":false,"Dynamic":false,"Explode":true,"GeoLoc":{"CSId":"","Has":false},"ModifiedTime":1712201716,"ScaleUniformly":false,"annotativeDwg":false,"insunits":1},"Checksum":"d88f1aab9224e4c60a61f65218dc7aab2924dd7a","Preview":{"Checksum":"d35cd613e66a3bde982c216c8322a204f5314c26","URL":"one-240v-duplex-y-orientation.dwg.png"}}}