{"Blocks":{"seh-exhaust-pipe":{"Att":{"Annotative":false,"Dynamic":false,"Explode":true,"InsUnit":1,"ScaleUniformly":false},"Previews":{"144_64_64_0":{"Checksum":"f9b538f955094a0843b590941bc8a72742b81727","URL":"32-inch-smart-hood-seh.dwg.seh-exhaust-pipe.144_64_64_0.png"}}}},"Header":{"Att":{"Annotative":false,"Dynamic":false,"Explode":true,"GeoLoc":{"CSId":"","Has":false},"ModifiedTime":1733805336,"ScaleUniformly":false,"annotativeDwg":false,"insunits":1},"Checksum":"563ce1481954431dafda576ea3a745954b873290","Preview":{"Checksum":"7725ef97624d794efea42a3858f7f5de81eaf872","URL":"32-inch-smart-hood-seh.dwg.png"}}}