{"Blocks":{"ceiling-gfci-duplex":{"Att":{"Annotative":false,"Dynamic":false,"Explode":true,"InsUnit":1,"ScaleUniformly":false},"Previews":{"144_64_64_0":{"Checksum":"c56c2d231f11a85db1582f1f4bfff280f63d1e60","URL":"ceiling-afci-gfci.dwg.ceiling-gfci-duplex.144_64_64_0.png"},"144_64_64_1":{"Checksum":"90836acd612ff72ed9c4cec33bb1333ce0f96662","URL":"ceiling-afci-gfci.dwg.ceiling-gfci-duplex.144_64_64_1.png"}}},"gfci-duplex":{"Att":{"Annotative":false,"Dynamic":false,"Explode":true,"InsUnit":1,"ScaleUniformly":false},"Previews":{"144_64_64_0":{"Checksum":"f202e4fc4185e7f8669c2e9ae58e53e6bba10b3b","URL":"ceiling-afci-gfci.dwg.gfci-duplex.144_64_64_0.png"},"144_64_64_1":{"Checksum":"a5d6578f11abf4b686d304d1581772369dccb7b9","URL":"ceiling-afci-gfci.dwg.gfci-duplex.144_64_64_1.png"}}}},"Header":{"Att":{"Annotative":false,"Dynamic":false,"Explode":true,"GeoLoc":{"CSId":"","Has":false},"ModifiedTime":1730999371,"ScaleUniformly":false,"annotativeDwg":false,"insunits":1},"Checksum":"6dd8de1348ddcc8b8aea532c884037567a470ce5","Preview":{"Checksum":"e5c39115638625c02d6ef4f893b860f1f0be2d23","URL":"ceiling-afci-gfci.dwg.png"}}}